kapla/cli/console.py
kapla/cli/datatypes.py
kapla/cli/errors.py
kapla/cli/projects.py
kapla/cli/repo.py
kapla/cli/utils.py
kapla_cli_core-3.6.1.dist-info/WHEEL
kapla_cli_core-3.6.1.dist-info/METADATA
kapla_cli_core-3.6.1.dist-info/RECORD
